multi_modal_tokenizers/__init__.py
multi_modal_tokenizers/image_processing.py
multi_modal_tokenizers/tokenizer.py
multi_modal_tokenizers/utils.py
multi_modal_tokenizers/tokenizers/__init__.py
multi_modal_tokenizers/tokenizers/base_tokenizers.py
multi_modal_tokenizers/tokenizers/dalle_tokenizer.py
multi_modal_tokenizers/tokenizers/mixed_modal_tokenizer.py
tests/__init__.py
tests/test_tokenizer.py
multi_modal_tokenizers-0.0.2.dist-info/METADATA
multi_modal_tokenizers-0.0.2.dist-info/WHEEL
multi_modal_tokenizers-0.0.2.dist-info/top_level.txt
multi_modal_tokenizers-0.0.2.dist-info/RECORD
