Metadata-Version: 2.1
Name: multi-modal-tokenizers
Version: 0.0.2
Summary: Multi-modal tokenizers for more than just text.
Home-page: https://github.com/anothy1/multi-modal-tokenizers
Author: Anthony Nguyen
License: UNKNOWN
Platform: UNKNOWN
Classifier: Programming Language :: Python :: 3
Classifier: License :: OSI Approved :: MIT License
Classifier: Operating System :: OS Independent
Requires-Python: >=3.8
Requires-Dist: torch
Requires-Dist: torchvision
Requires-Dist: Pillow
Requires-Dist: dall-e
Requires-Dist: huggingface-hub
Requires-Dist: safetensors
